mtasklite/__init__.py
mtasklite/constants.py
mtasklite/delayed_init.py
mtasklite/pool.py
mtasklite/pqdm.py
mtasklite/processes.py
mtasklite/threads.py
mtasklite/utils.py
mtasklite/version.py
mtasklite/tests/__init__.py
mtasklite/tests/run_all_unittests.py
mtasklite/tests/test_misc.py
mtasklite/tests/test_stateful.py
mtasklite/tests/test_stateless.py
mtasklite-0.3.5.dist-info/licenses/LICENSE
mtasklite-0.3.5.dist-info/METADATA
mtasklite-0.3.5.dist-info/WHEEL
mtasklite-0.3.5.dist-info/top_level.txt
mtasklite-0.3.5.dist-info/RECORD
