Metadata-Version: 2.4
Name: mtasklite
Version: 0.3.5
Summary: An pqdm-compatible (almost) extension that supports stateful worker pools with both sized and unsized iterables.
Author: Leonid Boytsov
Author-email: leo@boytsov.info
License: Apache 2.0
Project-URL: Homepage, https://github.com/searchivarius/py_mtasklite
Requires-Python: >=3.6
License-File: LICENSE
Requires-Dist: tqdm
Requires-Dist: multiprocess
Dynamic: author
Dynamic: author-email
Dynamic: description
Dynamic: description-content-type
Dynamic: license
Dynamic: license-file
Dynamic: project-url
Dynamic: requires-dist
Dynamic: requires-python
Dynamic: summary
